kovar/__init__.py
kovar/hello.py
kovar-0.0.1.dist-info/METADATA
kovar-0.0.1.dist-info/WHEEL
kovar-0.0.1.dist-info/top_level.txt
kovar-0.0.1.dist-info/RECORD
