Metadata-Version: 2.1
Name: kovar
Version: 0.0.1
Summary: A basic hello package
Home-page: UNKNOWN
Author: @kovar
Author-email: <jiri@kovar.cz>
License: UNKNOWN
Keywords: python,personal
Platform: UNKNOWN
Classifier: Development Status :: 1 - Planning
Classifier: Intended Audience :: Developers
Classifier: Programming Language :: Python :: 3
Classifier: Operating System :: Unix
Classifier: Operating System :: MacOS :: MacOS X
Classifier: Operating System :: Microsoft :: Windows
Requires-Dist: numpy
Requires-Dist: matplotlib
